lite_mamba/__init__.py
lite_mamba/causal_dilated_conv1d.py
lite_mamba/mamba_simple.py
lite_mamba/selective_scan.py
lite_mamba-0.1.8.dist-info/METADATA
lite_mamba-0.1.8.dist-info/WHEEL
lite_mamba-0.1.8.dist-info/top_level.txt
lite_mamba-0.1.8.dist-info/RECORD
