Metadata-Version: 2.4
Name: lite-mamba
Version: 0.1.8
Summary: Pure-PyTorch lightweight Mamba with multi-dilated causal conv front-end
Home-page: https://github.com/Mrrobi/lite_mamba
Author: Md Robiuddin
Author-email: mrrobi040@gmail.com
License: Apache-2.0
Project-URL: Homepage, https://github.com/Mrrobi/lite_mamba
Classifier: License :: OSI Approved :: Apache Software License
Classifier: Programming Language :: Python :: 3
Classifier: Programming Language :: Python :: 3 :: Only
Classifier: Programming Language :: Python :: 3.9
Classifier: Programming Language :: Python :: 3.10
Classifier: Programming Language :: Python :: 3.11
Classifier: Programming Language :: Python :: 3.12
Classifier: Intended Audience :: Science/Research
Classifier: Topic :: Scientific/Engineering :: Artificial Intelligence
Requires-Python: >=3.9
Requires-Dist: torch>=2.0
Requires-Dist: einops>=0.6
Dynamic: author
Dynamic: author-email
Dynamic: classifier
Dynamic: description
Dynamic: description-content-type
Dynamic: home-page
Dynamic: license
Dynamic: project-url
Dynamic: requires-dist
Dynamic: requires-python
Dynamic: summary
